MANIFEST.in
NEWS.txt
README.txt
setup.py
src/tunesweb/__init__.py
src/tunesweb.egg-info/PKG-INFO
src/tunesweb.egg-info/SOURCES.txt
src/tunesweb.egg-info/dependency_links.txt
src/tunesweb.egg-info/entry_points.txt
src/tunesweb.egg-info/not-zip-safe
src/tunesweb.egg-info/requires.txt
src/tunesweb.egg-info/top_level.txt