Metadata-Version: 1.0
Name: tunesweb
Version: 1.0b1
Summary: Control iTunes using your web browser from anywhere in the network
Home-page: http://bitbucket.org/srid/tunesweb
Author: srid
Author-email: srid@nearfar.org
License: MIT
Platform: UNKNOWN
